<?xml version="1.0"?>
<metadata xml:lang="en"><Esri><CreaDate>20230727</CreaDate><CreaTime>09412800</CreaTime><ArcGISFormat>1.0</ArcGISFormat><SyncOnce>TRUE</SyncOnce><ModDate>20240904</ModDate><ModTime>13305200</ModTime><scaleRange><minScale>150000000</minScale><maxScale>5000</maxScale></scaleRange><ArcGISProfile>ISO19139</ArcGISProfile></Esri><tool name="InterfaceLoadEstimation" displayname="5-Load Estimation" toolboxalias="" xmlns=""><arcToolboxHelpPath>c:\program files\arcgis\pro\Resources\Help\gp</arcToolboxHelpPath><parameters><param name="Types of contaminants" displayname="Types of contaminants" type="Required" direction="Input" datatype="String" expression="Nitrogen | Phosphorus | Nitrogen and Phosphorus"><dialogReference>&lt;DIV STYLE="text-align:Left;"&gt;&lt;DIV&gt;&lt;DIV&gt;&lt;P&gt;&lt;SPAN&gt;Nitrogen, phosphorus, or nitrogen and phosphorus.&lt;/SPAN&gt;&lt;/P&gt;&lt;/DIV&gt;&lt;/DIV&gt;&lt;/DIV&gt;</dialogReference></param><param name="Consideration of NH₄-N" displayname="Consideration of NH₄-N" type="Required" direction="Input" datatype="Boolean" expression="Consideration of NH₄-N"><dialogReference>&lt;DIV STYLE="text-align:Left;"&gt;&lt;P&gt;&lt;SPAN&gt;Consideration of NH₄&lt;/SPAN&gt;&lt;SPAN&gt;-N.&lt;/SPAN&gt;&lt;/P&gt;&lt;/DIV&gt;</dialogReference></param><param name="Risk Factor" displayname="Risk Factor" type="Required" direction="Input" datatype="Double" expression="Risk Factor"><dialogReference>&lt;DIV STYLE="text-align:Left;"&gt;&lt;DIV&gt;&lt;DIV&gt;&lt;P&gt;&lt;SPAN&gt;&lt;SPAN&gt;The values in the Mass Output Load column will be multiplied by the risk factor for each water body. The resulting number is then shown in the &lt;/SPAN&gt;&lt;/SPAN&gt;&lt;SPAN STYLE="font-weight:bold;"&gt;Mass Output Load &lt;/SPAN&gt;&lt;SPAN STYLE="font-weight:bold;"&gt;*&lt;/SPAN&gt;&lt;SPAN STYLE="font-weight:bold;"&gt; Risk Fac&lt;/SPAN&gt;&lt;SPAN STYLE="font-weight:bold;"&gt;tor&lt;/SPAN&gt;&lt;SPAN STYLE="font-weight:bold;"&gt;. &lt;/SPAN&gt;&lt;SPAN&gt;&lt;SPAN&gt;Column. The value of risk factor should be determined by the user. &lt;/SPAN&gt;&lt;/SPAN&gt;&lt;/P&gt;&lt;/DIV&gt;&lt;/DIV&gt;&lt;/DIV&gt;</dialogReference></param><param name="Input Plumes NO₃-N info" displayname="Input Plumes NO₃-N info (Point)" type="Required" direction="Input" datatype="Feature Layer" expression="Input Plumes NO₃-N info"><dialogReference>&lt;DIV STYLE="text-align:Left;"&gt;&lt;P&gt;&lt;SPAN&gt;Input Plumes NO₃&lt;/SPAN&gt;&lt;SPAN&gt;-N&lt;/SPAN&gt;&lt;SPAN&gt; info (Point)&lt;/SPAN&gt;&lt;/P&gt;&lt;/DIV&gt;</dialogReference></param><param name="Input Plumes NH₄-N info" displayname="Input Plumes NH₄-N info (Point)" type="Optional" direction="Input" datatype="Feature Layer" expression="{Input Plumes NH₄-N info}"><dialogReference>&lt;DIV STYLE="text-align:Left;"&gt;&lt;P&gt;&lt;SPAN&gt;Input Plumes NH₄&lt;/SPAN&gt;&lt;SPAN&gt;-N&lt;/SPAN&gt;&lt;SPAN&gt; info (Point)&lt;/SPAN&gt;&lt;/P&gt;&lt;/DIV&gt;</dialogReference></param><param name="Input Plumes PO₄-P info" displayname="Input Plumes PO₄-P info (Point)" type="Optional" direction="Input" datatype="Feature Layer" expression="{Input Plumes PO₄-P info}"><dialogReference>&lt;DIV STYLE="text-align:Left;"&gt;&lt;DIV&gt;&lt;P&gt;&lt;SPAN&gt;Input Plumes &lt;/SPAN&gt;&lt;SPAN&gt;PO&lt;/SPAN&gt;&lt;SPAN&gt;₄&lt;/SPAN&gt;&lt;SPAN&gt;-P&lt;/SPAN&gt;&lt;SPAN&gt; info (Point)&lt;/SPAN&gt;&lt;/P&gt;&lt;/DIV&gt;&lt;/DIV&gt;</dialogReference></param><param name="Output Results for NO₃-N" displayname="Output Results for NO₃-N" type="Required" direction="Output" datatype="File" expression="Output Results for NO₃-N"><dialogReference>&lt;DIV STYLE="text-align:Left;"&gt;&lt;P&gt;&lt;SPAN&gt;Output Results for NO₃&lt;/SPAN&gt;&lt;SPAN&gt;-N&lt;/SPAN&gt;&lt;/P&gt;&lt;/DIV&gt;</dialogReference></param><param name="Output Results for NH₄-N" displayname="Output Results for NH₄-N" type="Optional" direction="Output" datatype="File" expression="{Output Results for NH₄-N}"><dialogReference>&lt;DIV STYLE="text-align:Left;"&gt;&lt;P&gt;&lt;SPAN&gt;Output Results for NH₄&lt;/SPAN&gt;&lt;SPAN&gt;-N&lt;/SPAN&gt;&lt;/P&gt;&lt;/DIV&gt;</dialogReference></param><param name="Output Results for PO₄-P" displayname="Output Results for PO₄-P" type="Optional" direction="Output" datatype="File" expression="{Output Results for PO₄-P}"><dialogReference>&lt;DIV STYLE="text-align:Left;"&gt;&lt;DIV&gt;&lt;P&gt;&lt;SPAN&gt;Output Results for &lt;/SPAN&gt;&lt;SPAN&gt;PO&lt;/SPAN&gt;&lt;SPAN&gt;₄&lt;/SPAN&gt;&lt;SPAN&gt;-P&lt;/SPAN&gt;&lt;/P&gt;&lt;/DIV&gt;&lt;/DIV&gt;</dialogReference></param></parameters></tool><dataIdInfo><idCitation><resTitle>5-Load Estimation</resTitle></idCitation></dataIdInfo><distInfo><distributor><distorFormat><formatName>ArcToolbox Tool</formatName></distorFormat></distributor></distInfo><mdHrLv><ScopeCd value="005"/></mdHrLv><mdDateSt Sync="TRUE">20240904</mdDateSt></metadata>
